{
  "projectMetadata": {
    "name": "ProjectColdBrew",
    "fullName": "Cold Brew Recipe Calculator",
    "description": "A comprehensive web application for calculating optimal cold brew coffee recipes with user management, community features, and educational content."
  },
  "phases": [
    {
      "id": "phase0",
      "name": "DevOps Project Setup",
      "description": "Establish project foundation including repository setup, CI/CD pipelines, development environment configuration, and initial project structure for the Cold Brew Recipe Calculator app.",
      "timeframe": "Week 0",
      "features": [
        {
          "id": "feature0_1",
          "title": "DevOps Project Setup",
          "description": "Establish project foundation including repository setup, CI/CD pipelines, development environment configuration, and initial project structure for the Cold Brew Recipe Calculator app.",
          "pbis": [
            {
              "id": "pbi0_1",
              "title": "Repository and Project Structure Setup",
              "description": "Create and configure source code repositories, establish project folder structure, and set up development environment standards.",
              "effort": 5,
              "businessValue": 5,
              "tasks": [
                {
                  "title": "Create main source code repository",
                  "description": "Set up Git repository with appropriate branching strategy and access controls",
                  "remainingWork": 4
                },
                {
                  "title": "Establish project folder structure",
                  "description": "Create standardized folder structure for frontend, backend, documentation, and infrastructure code",
                  "remainingWork": 3
                },
                {
                  "title": "Configure repository settings and permissions",
                  "description": "Set up branch protection rules, pull request requirements, and team access permissions",
                  "remainingWork": 2
                },
                {
                  "title": "Create initial README and documentation structure",
                  "description": "Add project overview, setup instructions, and documentation templates",
                  "remainingWork": 3
                },
                {
                  "title": "Set up development environment configuration",
                  "description": "Create development environment setup scripts and configuration files",
                  "remainingWork": 4
                }
              ]
            },
            {
              "id": "pbi0_2",
              "title": "Continuous Integration Pipeline",
              "description": "Implement automated build and testing pipeline to ensure code quality and catch issues early in the development process.",
              "effort": 8,
              "businessValue": 4,
              "tasks": [
                {
                  "title": "Configure build automation",
                  "description": "Set up automated builds triggered by code commits and pull requests",
                  "remainingWork": 6
                },
                {
                  "title": "Implement automated testing pipeline",
                  "description": "Configure unit test execution and code coverage reporting in CI pipeline",
                  "remainingWork": 8
                },
                {
                  "title": "Set up code quality checks",
                  "description": "Integrate linting, code analysis, and security scanning tools",
                  "remainingWork": 4
                },
                {
                  "title": "Configure build notifications",
                  "description": "Set up notifications for build failures and success status reporting",
                  "remainingWork": 2
                },
                {
                  "title": "Create build status badges and reporting",
                  "description": "Add build status visibility and reporting dashboards",
                  "remainingWork": 3
                }
              ]
            },
            {
              "id": "pbi0_3",
              "title": "Development Environment Deployment",
              "description": "Set up initial deployment pipeline for development environment with basic CI/CD capabilities for early testing and validation.",
              "effort": 8,
              "businessValue": 3,
              "tasks": [
                {
                  "title": "Set up development hosting environment",
                  "description": "Configure cloud hosting resources for development environment deployment",
                  "remainingWork": 6
                },
                {
                  "title": "Create basic deployment pipeline",
                  "description": "Implement automated deployment to development environment on successful builds",
                  "remainingWork": 8
                },
                {
                  "title": "Configure environment variables and secrets",
                  "description": "Set up secure management of configuration and sensitive data for deployments",
                  "remainingWork": 4
                },
                {
                  "title": "Implement deployment rollback capability",
                  "description": "Add ability to quickly rollback deployments if issues are detected",
                  "remainingWork": 6
                },
                {
                  "title": "Set up deployment monitoring and health checks",
                  "description": "Implement basic monitoring to ensure deployment success and application health",
                  "remainingWork": 4
                }
              ]
            },
            {
              "id": "pbi0_4",
              "title": "Complete CI/CD Pipeline with Multi-Environment Support",
              "description": "Extend CI/CD pipeline to support multiple environments (staging, production) with approval workflows and advanced deployment strategies.",
              "effort": 13,
              "businessValue": 3,
              "tasks": [
                {
                  "title": "Set up staging environment",
                  "description": "Configure staging environment that mirrors production for pre-release testing",
                  "remainingWork": 8
                },
                {
                  "title": "Implement approval workflows",
                  "description": "Add manual approval gates for staging and production deployments",
                  "remainingWork": 6
                },
                {
                  "title": "Configure production deployment pipeline",
                  "description": "Set up secure, automated deployment pipeline for production environment",
                  "remainingWork": 10
                },
                {
                  "title": "Implement blue-green deployment strategy",
                  "description": "Add zero-downtime deployment capabilities with automatic failover",
                  "remainingWork": 12
                },
                {
                  "title": "Set up comprehensive monitoring and alerting",
                  "description": "Implement full monitoring stack with alerts for all environments",
                  "remainingWork": 8
                }
              ]
            }
          ]
        }
      ]
    },
    {
      "id": "phase1",
      "name": "Core Calculator and Basic UI",
      "description": "Implement the core brewing calculator functionality and basic user interface for the Cold Brew Recipe Calculator app. This phase includes recipe calculations, basic UI components, and fundamental app architecture.",
      "timeframe": "Weeks 1-4",
      "features": [
        {
          "id": "feature1_1",
          "title": "Core Calculator and Basic UI",
          "description": "Implement the core brewing calculator functionality and basic user interface for the Cold Brew Recipe Calculator app. This phase includes recipe calculations, basic UI components, and fundamental app architecture.",
          "pbis": [
            {
              "id": "pbi1_1",
              "title": "Recipe Calculation Engine",
              "description": "Develop algorithms for calculating optimal coffee-to-water ratios, steeping times, and strength adjustments. Support multiple brewing methods and batch size scaling.",
              "effort": 13,
              "businessValue": 5,
              "tasks": [
                {
                  "title": "Research coffee brewing ratios and formulas",
                  "description": "Research industry standards for cold brew ratios, steeping times, and strength calculations",
                  "remainingWork": 6
                },
                {
                  "title": "Design calculation algorithms",
                  "description": "Create mathematical formulas for ratio calculations and strength adjustments",
                  "remainingWork": 8
                },
                {
                  "title": "Implement core calculation functions",
                  "description": "Code the core calculation logic with input validation",
                  "remainingWork": 12
                },
                {
                  "title": "Add batch size scaling logic",
                  "description": "Implement functionality to scale recipes for different batch sizes",
                  "remainingWork": 6
                },
                {
                  "title": "Create unit tests for calculations",
                  "description": "Write comprehensive unit tests for all calculation functions",
                  "remainingWork": 8
                }
              ]
            },
            {
              "id": "pbi1_2",
              "title": "Basic User Interface Components",
              "description": "Create clean, intuitive UI components for recipe input, calculation display, and basic navigation. Focus on usability and responsive design.",
              "effort": 13,
              "businessValue": 5,
              "tasks": [
                {
                  "title": "Design UI wireframes and mockups",
                  "description": "Create wireframes for main calculator interface and navigation",
                  "remainingWork": 8
                },
                {
                  "title": "Set up project structure and dependencies",
                  "description": "Initialize project with chosen framework and configure build tools",
                  "remainingWork": 4
                },
                {
                  "title": "Implement main calculator input form",
                  "description": "Build form components for coffee amount, water volume, and strength selection",
                  "remainingWork": 10
                },
                {
                  "title": "Create results display component",
                  "description": "Design and implement component to show calculated ratios and instructions",
                  "remainingWork": 8
                },
                {
                  "title": "Add responsive design and basic styling",
                  "description": "Implement responsive CSS and ensure mobile compatibility",
                  "remainingWork": 10
                }
              ]
            },
            {
              "id": "pbi1_3",
              "title": "Brewing Timer and Countdown",
              "description": "Implement countdown timers for steeping periods with visual progress indicators and audio/visual alerts.",
              "effort": 8,
              "businessValue": 4,
              "tasks": [
                {
                  "title": "Design timer component interface",
                  "description": "Create UI design for timer display and controls",
                  "remainingWork": 4
                },
                {
                  "title": "Implement countdown timer logic",
                  "description": "Build JavaScript timer functionality with start/pause/reset",
                  "remainingWork": 8
                },
                {
                  "title": "Add visual progress indicators",
                  "description": "Create circular progress bars and time remaining displays",
                  "remainingWork": 6
                },
                {
                  "title": "Implement timer alerts and notifications",
                  "description": "Add audio alerts and browser notifications for timer completion",
                  "remainingWork": 4
                },
                {
                  "title": "Test timer accuracy and performance",
                  "description": "Validate timer precision and test on different devices",
                  "remainingWork": 3
                }
              ]
            }
          ]
        }
      ]
    },
    {
      "id": "phase2",
      "name": "User Accounts and Recipe Saving",
      "description": "Implement user authentication, profile management, and recipe persistence functionality. Enable users to save, organize, and retrieve their favorite brewing recipes.",
      "timeframe": "Weeks 5-8",
      "features": [
        {
          "id": "feature2_1",
          "title": "User Accounts and Recipe Saving",
          "description": "Implement user authentication, profile management, and recipe persistence functionality. Enable users to save, organize, and retrieve their favorite brewing recipes.",
          "pbis": [
            {
              "id": "pbi2_1",
              "title": "User Authentication and Profiles",
              "description": "Implement secure user registration, login, and profile management system with social authentication options.",
              "effort": 13,
              "businessValue": 4,
              "tasks": [
                {
                  "title": "Set up authentication service integration",
                  "description": "Choose and configure authentication provider (Firebase Auth, Auth0, etc.)",
                  "remainingWork": 6
                },
                {
                  "title": "Create registration and login forms",
                  "description": "Build user registration and login UI components",
                  "remainingWork": 8
                },
                {
                  "title": "Implement user profile management",
                  "description": "Create profile editing interface for user preferences",
                  "remainingWork": 8
                },
                {
                  "title": "Add social authentication options",
                  "description": "Integrate Google and Facebook login options",
                  "remainingWork": 6
                },
                {
                  "title": "Implement password reset functionality",
                  "description": "Add forgot password and reset password features",
                  "remainingWork": 4
                }
              ]
            },
            {
              "id": "pbi2_2",
              "title": "Recipe Save and Management System",
              "description": "Enable users to save, name, organize, and manage their brewing recipes with categories and search functionality.",
              "effort": 13,
              "businessValue": 5,
              "tasks": [
                {
                  "title": "Design database schema for recipes",
                  "description": "Create data models for recipes, user preferences, and brewing history",
                  "remainingWork": 8
                },
                {
                  "title": "Implement recipe saving functionality",
                  "description": "Add save recipe button and form for naming recipes",
                  "remainingWork": 6
                },
                {
                  "title": "Create recipe library interface",
                  "description": "Build UI to display and manage saved recipes",
                  "remainingWork": 10
                },
                {
                  "title": "Add recipe categorization and tagging",
                  "description": "Implement category system and custom tags for recipes",
                  "remainingWork": 6
                },
                {
                  "title": "Implement recipe search and filtering",
                  "description": "Add search functionality and filters for recipe management",
                  "remainingWork": 8
                }
              ]
            },
            {
              "id": "pbi2_3",
              "title": "Brewing History and Analytics",
              "description": "Track user brewing sessions, provide analytics on brewing patterns, and offer insights for improvement.",
              "effort": 13,
              "businessValue": 3,
              "tasks": [
                {
                  "title": "Design brewing session data model",
                  "description": "Create schema for tracking brewing sessions and outcomes",
                  "remainingWork": 4
                },
                {
                  "title": "Implement session logging functionality",
                  "description": "Add automatic logging of completed brewing sessions",
                  "remainingWork": 6
                },
                {
                  "title": "Create brewing history dashboard",
                  "description": "Build interface to view past brewing sessions and statistics",
                  "remainingWork": 10
                },
                {
                  "title": "Add brewing success rating system",
                  "description": "Allow users to rate and review their brewing results",
                  "remainingWork": 4
                },
                {
                  "title": "Generate brewing insights and recommendations",
                  "description": "Analyze patterns and suggest improvements",
                  "remainingWork": 8
                }
              ]
            }
          ]
        }
      ]
    },
    {
      "id": "phase3",
      "name": "Advanced Features and Polish",
      "description": "Implement advanced features including coffee bean database, community features, educational content, and application polish for production readiness.",
      "timeframe": "Weeks 9-12",
      "features": [
        {
          "id": "feature3_1",
          "title": "Advanced Features and Polish",
          "description": "Implement advanced features including coffee bean database, community features, educational content, and application polish for production readiness.",
          "pbis": [
            {
              "id": "pbi3_1",
              "title": "Coffee Bean Database and Recommendations",
              "description": "Build comprehensive database of coffee beans with flavor profiles, origin information, and brewing recommendations.",
              "effort": 21,
              "businessValue": 3,
              "tasks": [
                {
                  "title": "Research and compile coffee bean data",
                  "description": "Gather information on popular coffee beans and their characteristics",
                  "remainingWork": 12
                },
                {
                  "title": "Design bean database schema",
                  "description": "Create data structure for bean information and flavor profiles",
                  "remainingWork": 6
                },
                {
                  "title": "Implement bean selection interface",
                  "description": "Build UI for browsing and selecting coffee beans",
                  "remainingWork": 8
                },
                {
                  "title": "Add flavor profile matching system",
                  "description": "Create algorithm to match beans with desired flavor profiles",
                  "remainingWork": 10
                },
                {
                  "title": "Integrate bean data with calculations",
                  "description": "Adjust brewing recommendations based on selected bean type",
                  "remainingWork": 6
                }
              ]
            },
            {
              "id": "pbi3_2",
              "title": "Recipe Sharing and Community Platform",
              "description": "Enable users to share recipes, rate others' recipes, and participate in a community-driven brewing platform.",
              "effort": 21,
              "businessValue": 2,
              "tasks": [
                {
                  "title": "Design recipe sharing data model",
                  "description": "Create schema for public recipes and user interactions",
                  "remainingWork": 6
                },
                {
                  "title": "Implement recipe publishing feature",
                  "description": "Add functionality to make recipes public and shareable",
                  "remainingWork": 8
                },
                {
                  "title": "Create community recipe browser",
                  "description": "Build interface to discover and browse community recipes",
                  "remainingWork": 10
                },
                {
                  "title": "Add rating and review system",
                  "description": "Implement star ratings and text reviews for recipes",
                  "remainingWork": 8
                },
                {
                  "title": "Implement recipe import functionality",
                  "description": "Allow users to import and save community recipes",
                  "remainingWork": 6
                }
              ]
            },
            {
              "id": "pbi3_3",
              "title": "Educational Content and Brewing Guides",
              "description": "Provide comprehensive educational content including brewing techniques, coffee science, and step-by-step guides for beginners.",
              "effort": 21,
              "businessValue": 4,
              "tasks": [
                {
                  "title": "Create brewing technique content",
                  "description": "Write guides for different cold brew methods and techniques",
                  "remainingWork": 16
                },
                {
                  "title": "Design educational content interface",
                  "description": "Create UI for displaying tips, guides, and educational content",
                  "remainingWork": 8
                },
                {
                  "title": "Add interactive brewing tutorials",
                  "description": "Implement step-by-step guided brewing experiences",
                  "remainingWork": 12
                },
                {
                  "title": "Create grind size guide with visuals",
                  "description": "Build visual guide for coffee grind sizes and equipment",
                  "remainingWork": 8
                },
                {
                  "title": "Add coffee science explanations",
                  "description": "Include educational content about extraction science and brewing principles",
                  "remainingWork": 12
                }
              ]
            }
          ]
        }
      ]
    },
    {
      "id": "phase4",
      "name": "Testing, Deployment, and Launch",
      "description": "Comprehensive testing, performance optimization, deployment preparation, and launch activities for the Cold Brew Recipe Calculator app.",
      "timeframe": "Weeks 13-16",
      "features": [
        {
          "id": "feature4_1",
          "title": "Phase 4: Testing, Deployment, and Launch",
          "description": "Comprehensive testing, performance optimization, deployment preparation, and launch activities for the Cold Brew Recipe Calculator app.",
          "pbis": [
            {
              "id": "pbi4_1",
              "title": "Comprehensive Testing and Quality Assurance",
              "description": "Conduct thorough testing including unit tests, integration tests, user acceptance testing, and performance testing across all platforms.",
              "effort": 21,
              "businessValue": 5,
              "tasks": [
                {
                  "title": "Complete unit test coverage",
                  "description": "Ensure 90%+ unit test coverage for all core functionality",
                  "remainingWork": 16
                },
                {
                  "title": "Perform integration testing",
                  "description": "Test API integrations and database operations",
                  "remainingWork": 12
                },
                {
                  "title": "Conduct cross-browser testing",
                  "description": "Test application across major browsers and devices",
                  "remainingWork": 8
                },
                {
                  "title": "Execute user acceptance testing",
                  "description": "Conduct UAT with target users and stakeholders",
                  "remainingWork": 12
                },
                {
                  "title": "Performance testing and optimization",
                  "description": "Test load times, responsiveness, and optimize performance",
                  "remainingWork": 10
                }
              ]
            },
            {
              "id": "pbi4_2",
              "title": "Production Deployment and Infrastructure Setup",
              "description": "Set up production infrastructure, deployment pipelines, monitoring, and ensure scalability and security for the live application.",
              "effort": 21,
              "businessValue": 5,
              "tasks": [
                {
                  "title": "Set up production hosting environment",
                  "description": "Configure cloud hosting and production database",
                  "remainingWork": 12
                },
                {
                  "title": "Implement CI/CD deployment pipeline",
                  "description": "Set up automated build and deployment processes",
                  "remainingWork": 10
                },
                {
                  "title": "Configure monitoring and logging",
                  "description": "Implement application monitoring and error tracking",
                  "remainingWork": 8
                },
                {
                  "title": "Security audit and hardening",
                  "description": "Conduct security review and implement best practices",
                  "remainingWork": 12
                },
                {
                  "title": "Set up backup and disaster recovery",
                  "description": "Implement data backup strategies and recovery procedures",
                  "remainingWork": 8
                }
              ]
            },
            {
              "id": "pbi4_3",
              "title": "Launch Preparation and Go-to-Market",
              "description": "Prepare for application launch including app store submissions, marketing materials, documentation, and user onboarding.",
              "effort": 21,
              "businessValue": 4,
              "tasks": [
                {
                  "title": "Create app store listings and assets",
                  "description": "Prepare app store descriptions, screenshots, and promotional materials",
                  "remainingWork": 12
                },
                {
                  "title": "Develop user onboarding flow",
                  "description": "Create guided tour and tutorial for new users",
                  "remainingWork": 8
                },
                {
                  "title": "Write user documentation and help content",
                  "description": "Create comprehensive help documentation and FAQs",
                  "remainingWork": 16
                },
                {
                  "title": "Implement analytics and user tracking",
                  "description": "Set up user analytics and conversion tracking",
                  "remainingWork": 6
                },
                {
                  "title": "Execute soft launch and gather feedback",
                  "description": "Conduct limited release to gather initial user feedback",
                  "remainingWork": 8
                }
              ]
            }
          ]
        }
      ]
    }
  ]
}
